{
  "title": "A Comprehensive Review",
  "outline": [
    {
      "level": "H1",
      "text": "Advancements in Deep Learning for Automated",
      "page": 1
    },
    {
      "level": "H1",
      "text": "Diagnosis of Ophthalmic Diseases:",
      "page": 1
    },
    {
      "level": "H1",
      "text": "A Comprehensive Review",
      "page": 1
    },
    {
      "level": "H2",
      "text": "SHREEMAT KUMAR DASH",
      "page": 1
    },
    {
      "level": "H2",
      "text": "ASHIS DAS",
      "page": 1
    },
    {
      "level": "H2",
      "text": "INTRODUCTION",
      "page": 1
    },
    {
      "level": "H2",
      "text": "K. Dash et al.: Advancements in DL for Automated Diagnosis of Ophthalmic Diseases",
      "page": 2
    },
    {
      "level": "H2",
      "text": "METHODOLOGY",
      "page": 2
    },
    {
      "level": "H2",
      "text": "LITERATURE SEARCH",
      "page": 2
    },
    {
      "level": "H2",
      "text": "We conducted an extensive literature search using",
      "page": 2
    },
    {
      "level": "H2",
      "text": "Employed a combination of keywords, including ‘‘deep",
      "page": 2
    },
    {
      "level": "H2",
      "text": "INCLUSION CRITERIA",
      "page": 2
    },
    {
      "level": "H2",
      "text": "Clear inclusion criteria were established to select studies",
      "page": 2
    },
    {
      "level": "H2",
      "text": "This study focused on papers that specifically addressed",
      "page": 2
    },
    {
      "level": "H2",
      "text": "STUDY SELECTION",
      "page": 2
    },
    {
      "level": "H2",
      "text": "Titles and abstracts were screened to identify potentially",
      "page": 2
    },
    {
      "level": "H2",
      "text": "Studies that did not align with the scope of the review",
      "page": 2
    },
    {
      "level": "H2",
      "text": "FULL-TEXT REVIEW",
      "page": 2
    },
    {
      "level": "H2",
      "text": "A thorough examination of the full text of the selected",
      "page": 2
    },
    {
      "level": "H2",
      "text": "The methodologies, datasets used, and reported out-",
      "page": 2
    },
    {
      "level": "H2",
      "text": "DATA EXTRACTION",
      "page": 2
    },
    {
      "level": "H2",
      "text": "Key information was extracted from each selected",
      "page": 2
    },
    {
      "level": "H2",
      "text": "The extracted data were systematically organized to",
      "page": 2
    },
    {
      "level": "H2",
      "text": "QUALITY ASSESSMENT",
      "page": 2
    },
    {
      "level": "H2",
      "text": "The quality of each selected study was assessed based",
      "page": 2
    },
    {
      "level": "H2",
      "text": "Gave preferences for studies with robust methodologies",
      "page": 2
    },
    {
      "level": "H2",
      "text": "SYNTHESIS AND ANALYSIS",
      "page": 2
    },
    {
      "level": "H2",
      "text": "We synthesized the findings from the selected papers",
      "page": 2
    },
    {
      "level": "H2",
      "text": "The strengths and limitations of each study were",
      "page": 2
    },
    {
      "level": "H2",
      "text": "DISCUSSION AND CONCLUSIONS",
      "page": 2
    },
    {
      "level": "H2",
      "text": "The synthesized information is integrated into a cohesive",
      "page": 2
    },
    {
      "level": "H2",
      "text": "The review was concluded by outlining key takeaways",
      "page": 2
    },
    {
      "level": "H2",
      "text": "GLAUCOMA",
      "page": 2
    },
    {
      "level": "H2",
      "text": "K. Dash et al.: Advancements in DL for Automated Diagnosis of Ophthalmic Diseases",
      "page": 3
    },
    {
      "level": "H2",
      "text": "METHODOLOGY AND DATASET VARIABILITY",
      "page": 3
    },
    {
      "level": "H2",
      "text": "ARCHITECTURES AND MODELS",
      "page": 3
    },
    {
      "level": "H2",
      "text": "ARCHITECTURES",
      "page": 3
    },
    {
      "level": "H2",
      "text": "LEARNING",
      "page": 3
    },
    {
      "level": "H2",
      "text": "MODELS",
      "page": 3
    },
    {
      "level": "H2",
      "text": "TECHNIQUES",
      "page": 3
    },
    {
      "level": "H2",
      "text": "Chandrappa et al. proposed a system employing",
      "page": 3
    },
    {
      "level": "H2",
      "text": "K. Dash et al.: Advancements in DL for Automated Diagnosis of Ophthalmic Diseases",
      "page": 4
    },
    {
      "level": "H2",
      "text": "OR SURGICAL NEEDS",
      "page": 4
    },
    {
      "level": "H2",
      "text": "MODELS",
      "page": 4
    },
    {
      "level": "H2",
      "text": "SYSTEMS",
      "page": 4
    },
    {
      "level": "H2",
      "text": "DIAGNOSIS",
      "page": 4
    },
    {
      "level": "H2",
      "text": "DISORDERS",
      "page": 4
    },
    {
      "level": "H2",
      "text": "MODEL ARCHITECTURES AND COMPARATIVE",
      "page": 4
    },
    {
      "level": "H2",
      "text": "ANALYSIS",
      "page": 4
    },
    {
      "level": "H2",
      "text": "K. Dash et al.: Advancements in DL for Automated Diagnosis of Ophthalmic Diseases",
      "page": 5
    },
    {
      "level": "H2",
      "text": "LIMITATIONS",
      "page": 5
    },
    {
      "level": "H2",
      "text": "SUMMARY",
      "page": 5
    },
    {
      "level": "H2",
      "text": "K. Dash et al.: Advancements in DL for Automated Diagnosis of Ophthalmic Diseases",
      "page": 6
    },
    {
      "level": "H2",
      "text": "DIABETIC RETINOPATHY",
      "page": 6
    },
    {
      "level": "H2",
      "text": "Non-proliferative Diabetic Retinopathy (NPDR): In",
      "page": 6
    },
    {
      "level": "H2",
      "text": "Proliferative Diabetic Retinopathy (PDR): As the con-",
      "page": 6
    },
    {
      "level": "H2",
      "text": "Diabetic Macular Edema (DME): Swelling of the",
      "page": 6
    },
    {
      "level": "H2",
      "text": "METHODOLOGY AND DATASET VARIABILITY",
      "page": 6
    },
    {
      "level": "H2",
      "text": "S. Mishra et al. utilized the Kaggle APTOS dataset with",
      "page": 6
    },
    {
      "level": "H2",
      "text": "Das et al. evaluated 26 cutting-edge DL architectures for",
      "page": 6
    },
    {
      "level": "H2",
      "text": "Mohanty et al. proposed hybrid DL architectures for",
      "page": 6
    },
    {
      "level": "H2",
      "text": "Kalyani et al. introduced a novel capsule network",
      "page": 6
    },
    {
      "level": "H2",
      "text": "Bhandari et al. explored soft computing approaches,",
      "page": 6
    },
    {
      "level": "H2",
      "text": "Doshi et al. implemented GPU-accelerated DCNN for",
      "page": 6
    },
    {
      "level": "H2",
      "text": "Hemanth et al. proposed a mixed method combining",
      "page": 6
    },
    {
      "level": "H2",
      "text": "Usman et al. designed a model utilizing DL to",
      "page": 6
    },
    {
      "level": "H2",
      "text": "TECHNIQUES",
      "page": 6
    },
    {
      "level": "H2",
      "text": "Sivapriya et al. introduced a novel DR segmentation",
      "page": 6
    },
    {
      "level": "H2",
      "text": "K. Dash et al.: Advancements in DL for Automated Diagnosis of Ophthalmic Diseases",
      "page": 7
    },
    {
      "level": "H2",
      "text": "Atlas et al. suggested using DL to identify retinal",
      "page": 7
    },
    {
      "level": "H2",
      "text": "Islam et al. developed a DL method for detecting",
      "page": 7
    },
    {
      "level": "H2",
      "text": "Chetoui et al. utilized conceptual models and dif-",
      "page": 7
    },
    {
      "level": "H2",
      "text": "Özbay employed the Artificial Bee Colony (ABC) algo-",
      "page": 7
    },
    {
      "level": "H2",
      "text": "DETECTION",
      "page": 7
    },
    {
      "level": "H2",
      "text": "Shoaib et al. addressed the urgent need for early DR",
      "page": 7
    },
    {
      "level": "H2",
      "text": "Bosale et al. combined transfer learning with CNNs to",
      "page": 7
    },
    {
      "level": "H2",
      "text": "Al-Ahmadi et al. explored DR diagnosis in the Middle",
      "page": 7
    },
    {
      "level": "H2",
      "text": "Al-Absi et al. introduced DiaNet v2 to improve diabetes",
      "page": 7
    },
    {
      "level": "H2",
      "text": "APPROACHES",
      "page": 7
    },
    {
      "level": "H2",
      "text": "Saranya et al. proposed an automated model combining",
      "page": 7
    },
    {
      "level": "H2",
      "text": "Nguyen et al. addressed the global health issue of",
      "page": 7
    },
    {
      "level": "H2",
      "text": "Qureshi et al. utilized an active DL model, the updated",
      "page": 7
    },
    {
      "level": "H2",
      "text": "Gangwar",
      "page": 7
    },
    {
      "level": "H2",
      "text": "LEARNING ALGORITHMS",
      "page": 7
    },
    {
      "level": "H2",
      "text": "D. A. Hasan et al. investigated the use of machine",
      "page": 7
    },
    {
      "level": "H2",
      "text": "Dai et al. developed DeepDR Plus, a DL system with",
      "page": 7
    },
    {
      "level": "H2",
      "text": "Islam et al. conducted a systematic review and",
      "page": 7
    },
    {
      "level": "H2",
      "text": "MODEL ARCHITECTURE AND COMPARATIVE ANALYSIS",
      "page": 7
    },
    {
      "level": "H2",
      "text": "K. Dash et al.: Advancements in DL for Automated Diagnosis of Ophthalmic Diseases",
      "page": 8
    },
    {
      "level": "H2",
      "text": "K. Dash et al.: Advancements in DL for Automated Diagnosis of Ophthalmic Diseases",
      "page": 9
    },
    {
      "level": "H2",
      "text": "LIMITATIONS",
      "page": 9
    },
    {
      "level": "H2",
      "text": "SUMMARY",
      "page": 9
    },
    {
      "level": "H2",
      "text": "CATARACT",
      "page": 9
    },
    {
      "level": "H2",
      "text": "METHODOLOGY AND DATASET VARIABILITY",
      "page": 9
    },
    {
      "level": "H2",
      "text": "MODEL ARCHITECTURE AND COMPARATIVE ANALYSIS",
      "page": 9
    },
    {
      "level": "H2",
      "text": "K. Dash et al.: Advancements in DL for Automated Diagnosis of Ophthalmic Diseases",
      "page": 10
    },
    {
      "level": "H2",
      "text": "ARSLAN et al. used deep learning models to study",
      "page": 10
    },
    {
      "level": "H2",
      "text": "LIMITATIONS",
      "page": 10
    },
    {
      "level": "H2",
      "text": "K. Dash et al.: Advancements in DL for Automated Diagnosis of Ophthalmic Diseases",
      "page": 11
    },
    {
      "level": "H2",
      "text": "SUMMARY",
      "page": 11
    },
    {
      "level": "H2",
      "text": "AMBLYOPIA",
      "page": 11
    },
    {
      "level": "H2",
      "text": "K. Dash et al.: Advancements in DL for Automated Diagnosis of Ophthalmic Diseases",
      "page": 12
    },
    {
      "level": "H2",
      "text": "METHODOLOGY AND DATASET VARIABILITY",
      "page": 12
    },
    {
      "level": "H2",
      "text": "K. Dash et al.: Advancements in DL for Automated Diagnosis of Ophthalmic Diseases",
      "page": 13
    },
    {
      "level": "H2",
      "text": "MODEL ARCHITECTURE AND COMPARATIVE ANALYSIS",
      "page": 13
    },
    {
      "level": "H2",
      "text": "LIMITATIONS",
      "page": 13
    },
    {
      "level": "H2",
      "text": "K. Dash et al.: Advancements in DL for Automated Diagnosis of Ophthalmic Diseases",
      "page": 14
    },
    {
      "level": "H2",
      "text": "SUMMARY",
      "page": 14
    },
    {
      "level": "H2",
      "text": "AGE-RELATED MACULAR DEGENERATION",
      "page": 14
    },
    {
      "level": "H2",
      "text": "METHODOLOGY AND DATASET VARIABILITY",
      "page": 14
    },
    {
      "level": "H2",
      "text": "K. Dash et al.: Advancements in DL for Automated Diagnosis of Ophthalmic Diseases",
      "page": 15
    },
    {
      "level": "H2",
      "text": "MODEL ARCHITECTURE AND COMPARATIVE ANALYSIS",
      "page": 15
    },
    {
      "level": "H2",
      "text": "LIMITATIONS",
      "page": 15
    },
    {
      "level": "H2",
      "text": "SUMMARY",
      "page": 15
    },
    {
      "level": "H2",
      "text": "K. Dash et al.: Advancements in DL for Automated Diagnosis of Ophthalmic Diseases",
      "page": 16
    },
    {
      "level": "H2",
      "text": "K. Dash et al.: Advancements in DL for Automated Diagnosis of Ophthalmic Diseases",
      "page": 17
    },
    {
      "level": "H2",
      "text": "CONCLUSION",
      "page": 17
    },
    {
      "level": "H2",
      "text": "REFERENCES",
      "page": 17
    },
    {
      "level": "H2",
      "text": "S. Rachel, T. Anitha, T. Rajendran, and Y. A. Waji, ‘‘Segmentation",
      "page": 17
    },
    {
      "level": "H2",
      "text": "Healthcare Eng., vol. 2022, pp. 1–10, Feb. 2022. [Online]. Available:",
      "page": 17
    },
    {
      "level": "H2",
      "text": "Rizwan, ‘‘Glaucoma detection and classification using improved U-Net",
      "page": 17
    },
    {
      "level": "H2",
      "text": "M. Basha, ‘‘Automated glaucoma detection from fundus images using",
      "page": 17
    },
    {
      "level": "H2",
      "text": "Sengodan, M. Murugappan, and S. Misra, Eds., Singapore: Springer,",
      "page": 17
    },
    {
      "level": "H2",
      "text": "Mech. Med. Biol., vol. 20, no. 1, Feb. 2020, Art. no. 1950065.",
      "page": 17
    },
    {
      "level": "H2",
      "text": "Unberath, and J. Yohannan, ‘‘Deep learning-based identification of eyes",
      "page": 17
    },
    {
      "level": "H2",
      "text": "M. Ilyas, ‘‘Automatic diagnosis of glaucoma from retinal images using",
      "page": 17
    },
    {
      "level": "H2",
      "text": "K. Dash et al.: Advancements in DL for Automated Diagnosis of Ophthalmic Diseases",
      "page": 18
    },
    {
      "level": "H2",
      "text": "L. Rao, S. Dasari, M. Riyazuddin, D. Chang, S. Nagaraj, C. C. Tham,",
      "page": 18
    },
    {
      "level": "H2",
      "text": "Roy, ‘‘Glaucoma diagnosis using multi-feature analysis and a deep",
      "page": 18
    },
    {
      "level": "H2",
      "text": "T. Rauf, ‘‘A novel hybrid approach based on deep CNN to detect",
      "page": 18
    },
    {
      "level": "H2",
      "text": "N. Weinreb, C. A. Girkin, J. M. Liebmann, and L. M. Zangwill,",
      "page": 18
    },
    {
      "level": "H2",
      "text": "W. Jeoung, ‘‘Estimating visual field loss from monoscopic optic disc",
      "page": 18
    },
    {
      "level": "H2",
      "text": "P. Costa, and F. A. Medeiros, ‘‘Detecting retinal nerve fibre layer",
      "page": 18
    },
    {
      "level": "H2",
      "text": "Karamitsos, and A. Kanavos, ‘‘Using deep learning architectures for",
      "page": 18
    },
    {
      "level": "H2",
      "text": "L. Peng, S. C. Satapathy, and Y. D. Zhang, Eds., Singapore: Springer,",
      "page": 18
    },
    {
      "level": "H2",
      "text": "Bashir, M. M. El Shafei, N. El Hajj, and T. Alam, ‘‘DiaNet v2",
      "page": 18
    },
    {
      "level": "H2",
      "text": "Hamzah, Y. Liu, and X. Wang, ‘‘A deep learning system for predicting",
      "page": 18
    },
    {
      "level": "H2",
      "text": "S. Mubarak, O. A. Omer, F. E. A. El-Samie, and H. Esmaiel, ‘‘Deep",
      "page": 18
    },
    {
      "level": "H2",
      "text": "R. Zebari, and A. H. Alkhayyat, ‘‘Machine learning-based diabetic",
      "page": 18
    },
    {
      "level": "H2",
      "text": "K. Dash et al.: Advancements in DL for Automated Diagnosis of Ophthalmic Diseases",
      "page": 19
    },
    {
      "level": "H2",
      "text": "Reiter, S. S. Vedula, H. Ali, and S. Sikder, ‘‘Assessment of",
      "page": 19
    },
    {
      "level": "H2",
      "text": "B. Wiratama, and I. D. S. Ubaidah, ‘‘Cataract classification based",
      "page": 19
    },
    {
      "level": "H2",
      "text": "Ghatak, Eds., Singapore: Springer, 2021, doi: 10.1007/978-981-",
      "page": 19
    },
    {
      "level": "H2",
      "text": "Al Hejaili, and U. Ghulam Mohammad, ‘‘CD-FL: Cataract images",
      "page": 19
    },
    {
      "level": "H2",
      "text": "S. Korade, ‘‘Automated cataract disease detection on anterior segment",
      "page": 19
    },
    {
      "level": "H2",
      "text": "S. Reddy, V. K. Prasad, J. Wang, and K. Reddy, Eds., Singapore:",
      "page": 19
    },
    {
      "level": "H2",
      "text": "P. Goyal, Eds., Cham, Switzerland: Springer, 2022, doi: 10.1007/978-",
      "page": 19
    },
    {
      "level": "H2",
      "text": "Yoon, and D. D.-J. Hwang, ‘‘Classifying neovascular age-related",
      "page": 19
    },
    {
      "level": "H2",
      "text": "Raman, and M. F. Beg, ‘‘Clinical explainable differential diagnosis",
      "page": 19
    },
    {
      "level": "H2",
      "text": "He was a Research Intern with Indian",
      "page": 20
    },
    {
      "level": "H2",
      "text": "K. Dash et al.: Advancements in DL for Automated Diagnosis of Ophthalmic Diseases",
      "page": 20
    },
    {
      "level": "H2",
      "text": "Yokota, M. Akiba, A. Tsujikawa, M. Takahashi, and Y. Kurimoto,",
      "page": 20
    },
    {
      "level": "H2",
      "text": "Y. Chew, and Z. Lu, ‘‘DeepSeeNet: A deep learning model for",
      "page": 20
    },
    {
      "level": "H2",
      "text": "Basu, D. Plewczynski, Eds., Singapore: Springer, 2021, pp. 433–441,",
      "page": 20
    },
    {
      "level": "H2",
      "text": "T. Thavikulwat, E. Chew, and C. Cukras, ‘‘Retinal layer segmentation",
      "page": 20
    },
    {
      "level": "H2",
      "text": "SHREEMAT",
      "page": 20
    },
    {
      "level": "H2",
      "text": "KUMAR",
      "page": 20
    },
    {
      "level": "H2",
      "text": "DASH",
      "page": 20
    },
    {
      "level": "H2",
      "text": "AZIZ",
      "page": 20
    },
    {
      "level": "H2",
      "text": "NANTHAAMORNPHONG",
      "page": 20
    }
  ]
}